workshop/modulos/4_Hardware/4_2_SPWM/spwm.v
/*------------------------------------------------------------------------
---- Modules:  counter, PWM_generator, RAM_DUAL and spwm              ----
---- Description: SPWM generator without PLL                          ----
---- Author/s:  Ramiro A. Ghignone                                    ----
---- Last revision: Sep. 2023                                         ----
---- Dependencies:  None                                              ----
------------------------------------------------------------------------*/

/**************************** Modulo Contador *******************************/

//Parametros y E/S
module counter #(parameter N_bits = 4) (

    //Clock y reset
    input  wire clk,
    input  wire rst,

    //Estado del contador
    output reg[N_bits-1:0] count
);

//Proceso asincronico
always @(posedge clk or posedge rst) begin
    if (rst == 1'b1) begin
        count <= 0;
    end else begin
        count <= count + 1;
    end
end

endmodule //counter

/************************** Modulo Generador PWM ****************************/

//Parametros y E/S
module PWM_generator #(parameter N_bits = 8) (

    // Clock y reset
    input wire clk,
    input wire rst,

    // Duty cycle
    input wire[N_bits-1 : 0] duty,

    // Salida
    output wire PWM_out
);

//Conexiones del contador interno
wire[N_bits-1 : 0] int_cnt_conn;

//Instanciar contador interno
counter int_cnt (.clk(clk),.rst(rst),.count(int_cnt_conn));
defparam int_cnt.N_bits = N_bits;

//Comparador de salida
assign PWM_out = (int_cnt_conn < duty)?(1'b1):(1'b0);

endmodule //PWM_generator

/******************************** Memoria RAM ********************************/

module RAM_DUAL 

  #(parameter WORD_LENGTH = 8,	  //Bits de cada palabra
    parameter ADDR_LENGTH = 8,	  //Bits de direcciones
    parameter MEM_INIT_FILE = "mem_data.mem"  //Archivo de inicializacion de memoria
    )

  (input wire w_clk,				            //Write clock
   input wire r_clk,							//Read clock
   input wire write,			                  //Write enable
   input [ADDR_LENGTH-1 : 0] w_addr,	        //Write address
   input [ADDR_LENGTH-1 : 0] r_addr,	        //Read address
   input wire [WORD_LENGTH-1 : 0] data_in,		//Dato de entrada
   output reg [WORD_LENGTH-1 : 0] data_out);    //Dato de salida
  
  //Bloque de memoria (** denota potencia)
  reg[WORD_LENGTH-1:0] MEMORY[0:2**ADDR_LENGTH-1];

  //LEER EL CONTENIDO DE LA MEMORIA DESDE UN ARCHIVO .mem
    initial begin
        $readmemh(MEM_INIT_FILE, MEMORY);
    end
  
  // Lectura (dominio w_clk)
  always @(posedge w_clk) begin
    if (write==1'b1) begin
      MEMORY[w_addr] <= data_in;
    end
  end
  
  //Escritura (dominio r_clk)
  always @(posedge r_clk) begin
    data_out <= MEMORY[r_addr];
  end

endmodule

/************************** Modulador SPWM (sin PLL) **************************/

module spwm (
    input wire clk,
    input wire rst,
    output wire pwm_out,
    output wire[2:0] dummy
);

// Negar entrada reset
wire global_rst;
assign global_rst = ~rst;

// Anular los otros 3 LEDs
assign dummy = 3'b000;

// Parametros internos del modulo
parameter MEM_CLK_DIVIDER_BITS = 19;
parameter ADDRESS_BITS  = 8;
parameter MEM_WORD_BITS = 8;

// Linea interna de clock para barrido de memoria
wire[MEM_CLK_DIVIDER_BITS-1:0] internal_mem_clk;

// Direccion de memoria de lectura
wire[ADDRESS_BITS-1:0] addr;

// Duty cycle interno
wire[MEM_WORD_BITS-1:0] dc;

////// Instanciar y conectar componentes

// Instanciar divisor de frecuencia para obtener un clock de 190 Hz
counter divisor_freq(.clk(clk),
                     .rst(global_rst),
                     .count(internal_mem_clk));
defparam divisor_freq.N_bits = MEM_CLK_DIVIDER_BITS;

// Instanciar contador para el barrido de la memoria
counter barrido_mem(.clk(internal_mem_clk[MEM_CLK_DIVIDER_BITS-1]),
                    .rst(global_rst),
                    .count(addr));
defparam barrido_mem.N_bits = ADDRESS_BITS;

// Instanciar memoria RAM
RAM_DUAL my_ram(.r_clk(clk),
               .w_clk(clk),
               .write(1'b0),
               .w_addr(addr),
               .r_addr(addr),
               .data_in(),
               .data_out(dc));

defparam my_ram.WORD_LENGTH = MEM_WORD_BITS;
defparam my_ram.ADDR_LENGTH = ADDRESS_BITS;

// Instanciar generador PWM
PWM_generator pwm(.clk(clk),
                  .rst(global_rst),
                  .duty(dc),
                  .PWM_out(pwm_out));
defparam pwm.N_bits = MEM_WORD_BITS;

endmodule

workshop/modulos/4_Hardware/4_2_SPWM/spwm_tb.v
/*------------------------------------------------------------------------
---- Modules:  test                                                   ----
---- Description: testbench for SPWM generator without PLL            ----
---- Author/s:  Ramiro A. Ghignone                                    ----
---- Last revision: Sep. 2023                                         ----
---- Dependencies:                                                    ----
----     spwm.v                                                       ----
------------------------------------------------------------------------*/

`include "spwm.v"

module test;

// Estimulos
reg clk;
reg rst;
wire pwm_out;
wire[2:0] dummy;

// DUT
spwm dut(  
    .clk(clk),
    .rst(rst),
    .pwm_out(pwm_out),
    .dummy(dummy)
);

// Reducir la division de frecuencia
defparam dut.MEM_CLK_DIVIDER_BITS = 4;

// Generacion clock
always #1 clk = !clk;

initial begin
    $dumpfile("test.vcd");
    $dumpvars(0,test); //Abrir archivo

    #0 rst <= 1'b0;
    #0 clk <= 1'b0;
    #2 rst <= 1'b1; // RST NEGADO !!

    #32768 $finish;
end

endmodule

workshop/modulos/4_Hardware/4_2_SPWM/test.vcd
$date
	Fri Jun  6 18:36:29 2025
$end
$version
	Icarus Verilog
$end
$timescale
	1s
$end
$scope module test $end
$var wire 3 ! dummy [2:0] $end
$var wire 1 " pwm_out $end
$var reg 1 # clk $end
$var reg 1 $ rst $end
$scope module dut $end
$var wire 1 # clk $end
$var wire 3 % dummy [2:0] $end
$var wire 1 & global_rst $end
$var wire 1 $ rst $end
$var wire 1 " pwm_out $end
$var wire 4 ' internal_mem_clk [3:0] $end
$var wire 8 ( dc [7:0] $end
$var wire 8 ) addr [7:0] $end
$scope module barrido_mem $end
$var wire 1 * clk $end
$var wire 1 & rst $end
$var reg 8 + count [7:0] $end
$upscope $end
$scope module divisor_freq $end
$var wire 1 # clk $end
$var wire 1 & rst $end
$var reg 4 , count [3:0] $end
$upscope $end
$scope module my_ram $end
$var wire 8 - data_in [7:0] $end
$var wire 8 . r_addr [7:0] $end
$var wire 1 # r_clk $end
$var wire 8 / w_addr [7:0] $end
$var wire 1 # w_clk $end
$var wire 1 0 write $end
$var reg 8 1 data_out [7:0] $end
$upscope $end
$scope module pwm $end
$var wire 1 # clk $end
$var wire 8 2 duty [7:0] $end
$var wire 1 & rst $end
$var wire 8 3 int_cnt_conn [7:0] $end
$var wire 1 " PWM_out $end
$scope module int_cnt $end
$var wire 1 # clk $end
$var wire 1 & rst $end
$var reg 8 4 count [7:0] $end
$upscope $end
$upscope $end
$upscope $end
$upscope $end
$enddefinitions $end
#0
$dumpvars
b0 4
b0 3
bx 2
bx 1
00
b0 /
b0 .
bz -
b0 ,
b0 +
0*
b0 )
bx (
b0 '
1&
b0 %
0$
0#
x"
b0 !
$end
#1
1"
b10000000 (
b10000000 1
b10000000 2
1#
#2
0&
1$
0#
#3
b1 '
b1 ,
b1 3
b1 4
1#
#4
0#
#5
b10 3
b10 4
b10 '
b10 ,
1#
#6
0#
#7
b11 '
b11 ,
b11 3
b11 4
1#
#8
0#
#9
b100 3
b100 4
b100 '
b100 ,
1#
#10
0#
#11
b101 '
b101 ,
b101 3
b101 4
1#
#12
0#
#13
b110 3
b110 4
b110 '
b110 ,
1#
#14
0#
#15
b111 '
b111 ,
b111 3
b111 4
1#
#16
0#
#17
b1 )
b1 +
b1 .
b1 /
1*
b1000 3
b1000 4
b1000 '
b1000 ,
1#
#18
0#
#19
b1001 '
b1001 ,
b1001 3
b1001 4
b10000011 (
b10000011 1
b10000011 2
1#
#20
0#
#21
b1010 3
b1010 4
b1010 '
b1010 ,
1#
#22
0#
#23
b1011 '
b1011 ,
b1011 3
b1011 4
1#
#24
0#
#25
b1100 3
b1100 4
b1100 '
b1100 ,
1#
#26
0#
#27
b1101 '
b1101 ,
b1101 3
b1101 4
1#
#28
0#
#29
b1110 3
b1110 4
b1110 '
b1110 ,
1#
#30
0#
#31
b1111 '
b1111 ,
b1111 3
b1111 4
1#
#32
0#
#33
0*
b10000 3
b10000 4
b0 '
b0 ,
1#
#34
0#
#35
b1 '
b1 ,
b10001 3
b10001 4
1#
#36
0#
#37
b10010 3
b10010 4
b10 '
b10 ,
1#
#38
0#
#39
b11 '
b11 ,
b10011 3
b10011 4
1#
#40
0#
#41
b10100 3
b10100 4
b100 '
b100 ,
1#
#42
0#
#43
b101 '
b101 ,
b10101 3
b10101 4
1#
#44
0#
#45
b10110 3
b10110 4
b110 '
b110 ,
1#
#46
0#
#47
b111 '
b111 ,
b10111 3
b10111 4
1#
#48
0#
#49
b10 )
b10 +
b10 .
b10 /
1*
b11000 3
b11000 4
b1000 '
b1000 ,
1#
#50
0#
#51
b1001 '
b1001 ,
b11001 3
b11001 4
b10000110 (
b10000110 1
b10000110 2
1#
#52
0#
#53
b11010 3
b11010 4
b1010 '
b1010 ,
1#
#54
0#
#55
b1011 '
b1011 ,
b11011 3
b11011 4
1#
#56
0#
#57
b11100 3
b11100 4
b1100 '
b1100 ,
1#
#58
0#
#59
b1101 '
b1101 ,
b11101 3
b11101 4
1#
#60
0#
#61
b11110 3
b11110 4
b1110 '
b1110 ,
1#
#62
0#
#63
b1111 '
b1111 ,
b11111 3
b11111 4
1#
#64
0#
#65
0*
b100000 3
b100000 4
b0 '
b0 ,
1#
#66
0#
#67
b1 '
b1 ,
b100001 3
b100001 4
1#
#68
0#
#69
b100010 3
b100010 4
b10 '
b10 ,
1#
#70
0#
#71
b11 '
b11 ,
b100011 3
b100011 4
1#
#72
0#
#73
b100100 3
b100100 4
b100 '
b100 ,
1#
#74
0#
#75
b101 '
b101 ,
b100101 3
b100101 4
1#
#76
0#
#77
b100110 3
b100110 4
b110 '
b110 ,
1#
#78
0#
#79
b111 '
b111 ,
b100111 3
b100111 4
1#
#80
0#
#81
b11 )
b11 +
b11 .
b11 /
1*
b101000 3
b101000 4
b1000 '
b1000 ,
1#
#82
0#
#83
b1001 '
b1001 ,
b101001 3
b101001 4
b10001001 (
b10001001 1
b10001001 2
1#
#84
0#
#85
b101010 3
b101010 4
b1010 '
b1010 ,
1#
#86
0#
#87
b1011 '
b1011 ,
b101011 3
b101011 4
1#
#88
0#
#89
b101100 3
b101100 4
b1100 '
b1100 ,
1#
#90
0#
#91
b1101 '
b1101 ,
b101101 3
b101101 4
1#
#92
0#
#93
b101110 3
b101110 4
b1110 '
b1110 ,
1#
#94
0#
#95
b1111 '
b1111 ,
b101111 3
b101111 4
1#
#96
0#
#97
0*
b110000 3
b110000 4
b0 '
b0 ,
1#
#98
0#
#99
b1 '
b1 ,
b110001 3
b110001 4
1#
#100
0#
#101
b110010 3
b110010 4
b10 '
b10 ,
1#
#102
0#
#103
b11 '
b11 ,
b110011 3
b110011 4
1#
#104
0#
#105
b110100 3
b110100 4
b100 '
b100 ,
1#
#106
0#
#107
b101 '
b101 ,
b110101 3
b110101 4
1#
#108
0#
#109
b110110 3
b110110 4
b110 '
b110 ,
1#
#110
0#
#111
b111 '
b111 ,
b110111 3
b110111 4
1#
#112
0#
#113
b100 )
b100 +
b100 .
b100 /
1*
b111000 3
b111000 4
b1000 '
b1000 ,
1#
#114
0#
#115
b1001 '
b1001 ,
b111001 3
b111001 4
b10001100 (
b10001100 1
b10001100 2
1#
#116
0#
#117
b111010 3
b111010 4
b1010 '
b1010 ,
1#
#118
0#
#119
b1011 '
b1011 ,
b111011 3
b111011 4
1#
#120
0#
#121
b111100 3
b111100 4
b1100 '
b1100 ,
1#
#122
0#
#123
b1101 '
b1101 ,
b111101 3
b111101 4
1#
#124
0#
#125
b111110 3
b111110 4
b1110 '
b1110 ,
1#
#126
0#
#127
b1111 '
b1111 ,
b111111 3
b111111 4
1#
#128
0#
#129
0*
b1000000 3
b1000000 4
b0 '
b0 ,
1#
#130
0#
#131
b1 '
b1 ,
b1000001 3
b1000001 4
1#
#132
0#
#133
b1000010 3
b1000010 4
b10 '
b10 ,
1#
#134
0#
#135
b11 '
b11 ,
b1000011 3
b1000011 4
1#
#136
0#
#137
b1000100 3
b1000100 4
b100 '
b100 ,
1#
#138
0#
#139
b101 '
b101 ,
b1000101 3
b1000101 4
1#
#140
0#
#141
b1000110 3
b1000110 4
b110 '
b110 ,
1#
#142
0#
#143
b111 '
b111 ,
b1000111 3
b1000111 4
1#
#144
0#
#145
b101 )
b101 +
b101 .
b101 /
1*
b1001000 3
b1001000 4
b1000 '
b1000 ,
1#
#146
0#
#147
b1001 '
b1001 ,
b1001001 3
b1001001 4
b10001111 (
b10001111 1
b10001111 2
1#
#148
0#
#149
b1001010 3
b1001010 4
b1010 '
b1010 ,
1#
#150
0#
#151
b1011 '
b1011 ,
b1001011 3
b1001011 4
1#
#152
0#
#153
b1001100 3
b1001100 4
b1100 '
b1100 ,
1#
#154
0#
#155
b1101 '
b1101 ,
b1001101 3
b1001101 4
1#
#156
0#
#157
b1001110 3
b1001110 4
b1110 '
b1110 ,
1#
#158
0#
#159
b1111 '
b1111 ,
b1001111 3
b1001111 4
1#
#160
0#
#161
0*
b1010000 3
b1010000 4
b0 '
b0 ,
1#
#162
0#
#163
b1 '
b1 ,
b1010001 3
b1010001 4
1#
#164
0#
#165
b1010010 3
b1010010 4
b10 '
b10 ,
1#
#166
0#
#167
b11 '
b11 ,
b1010011 3
b1010011 4
1#
#168
0#
#169
b1010100 3
b1010100 4
b100 '
b100 ,
1#
#170
0#
#171
b101 '
b101 ,
b1010101 3
b1010101 4
1#
#172
0#
#173
b1010110 3
b1010110 4
b110 '
b110 ,
1#
#174
0#
#175
b111 '
b111 ,
b1010111 3
b1010111 4
1#
#176
0#
#177
b110 )
b110 +
b110 .
b110 /
1*
b1011000 3
b1011000 4
b1000 '
b1000 ,
1#
#178
0#
#179
b1001 '
b1001 ,
b1011001 3
b1011001 4
b10010010 (
b10010010 1
b10010010 2
1#
#180
0#
#181
b1011010 3
b1011010 4
b1010 '
b1010 ,
1#
#182
0#
#183
b1011 '
b1011 ,
b1011011 3
b1011011 4
1#
#184
0#
#185
b1011100 3
b1011100 4
b1100 '
b1100 ,
1#
#186
0#
#187
b1101 '
b1101 ,
b1011101 3
b1011101 4
1#
#188
0#
#189
b1011110 3
b1011110 4
b1110 '
b1110 ,
1#
#190
0#
#191
b1111 '
b1111 ,
b1011111 3
b1011111 4
1#
#192
0#
#193
0*
b1100000 3
b1100000 4
b0 '
b0 ,
1#
#194
0#
#195
b1 '
b1 ,
b1100001 3
b1100001 4
1#
#196
0#
#197
b1100010 3
b1100010 4
b10 '
b10 ,
1#
#198
0#
#199
b11 '
b11 ,
b1100011 3
b1100011 4
1#
#200
0#
#201
b1100100 3
b1100100 4
b100 '
b100 ,
1#
#202
0#
#203
b101 '
b101 ,
b1100101 3
b1100101 4
1#
#204
0#
#205
b1100110 3
b1100110 4
b110 '
b110 ,
1#
#206
0#
#207
b111 '
b111 ,
b1100111 3
b1100111 4
1#
#208
0#
#209
b111 )
b111 +
b111 .
b111 /
1*
b1101000 3
b1101000 4
b1000 '
b1000 ,
1#
#210
0#
#211
b1001 '
b1001 ,
b1101001 3
b1101001 4
b10010101 (
b10010101 1
b10010101 2
1#
#212
0#
#213
b1101010 3
b1101010 4
b1010 '
b1010 ,
1#
#214
0#
#215
b1011 '
b1011 ,
b1101011 3
b1101011 4
1#
#216
0#
#217
b1101100 3
b1101100 4
b1100 '
b1100 ,
1#
#218
0#
#219
b1101 '
b1101 ,
b1101101 3
b1101101 4
1#
#220
0#
#221
b1101110 3
b1101110 4
b1110 '
b1110 ,
1#
#222
0#
#223
b1111 '
b1111 ,
b1101111 3
b1101111 4
1#
#224
0#
#225
0*
b1110000 3
b1110000 4
b0 '
b0 ,
1#
#226
0#
#227
b1 '
b1 ,
b1110001 3
b1110001 4
1#
#228
0#
#229
b1110010 3
b1110010 4
b10 '
b10 ,
1#
#230
0#
#231
b11 '
b11 ,
b1110011 3
b1110011 4
1#
#232
0#
#233
b1110100 3
b1110100 4
b100 '
b100 ,
1#
#234
0#
#235
b101 '
b101 ,
b1110101 3
b1110101 4
1#
#236
0#
#237
b1110110 3
b1110110 4
b110 '
b110 ,
1#
#238
0#
#239
b111 '
b111 ,
b1110111 3
b1110111 4
1#
#240
0#
#241
b1000 )
b1000 +
b1000 .
b1000 /
1*
b1111000 3
b1111000 4
b1000 '
b1000 ,
1#
#242
0#
#243
b1001 '
b1001 ,
b1111001 3
b1111001 4
b10011000 (
b10011000 1
b10011000 2
1#
#244
0#
#245
b1111010 3
b1111010 4
b1010 '
b1010 ,
1#
#246
0#
#247
b1011 '
b1011 ,
b1111011 3
b1111011 4
1#
#248
0#
#249
b1111100 3
b1111100 4
b1100 '
b1100 ,
1#
#250
0#
#251
b1101 '
b1101 ,
b1111101 3
b1111101 4
1#
#252
0#
#253
b1111110 3
b1111110 4
b1110 '
b1110 ,
1#
#254
0#
#255
b1111 '
b1111 ,
b1111111 3
b1111111 4
1#
#256
0#
#257
0*
b10000000 3
b10000000 4
b0 '
b0 ,
1#
#258
0#
#259
b1 '
b1 ,
b10000001 3
b10000001 4
1#
#260
0#
#261
b10000010 3
b10000010 4
b10 '
b10 ,
1#
#262
0#
#263
b11 '
b11 ,
b10000011 3
b10000011 4
1#
#264
0#
#265
b10000100 3
b10000100 4
b100 '
b100 ,
1#
#266
0#
#267
b101 '
b101 ,
b10000101 3
b10000101 4
1#
#268
0#
#269
b10000110 3
b10000110 4
b110 '
b110 ,
1#
#270
0#
#271
b111 '
b111 ,
b10000111 3
b10000111 4
1#
#272
0#
#273
b1001 )
b1001 +
b1001 .
b1001 /
1*
b10001000 3
b10001000 4
b1000 '
b1000 ,
1#
#274
0#
#275
b1001 '
b1001 ,
b10001001 3
b10001001 4
b10011100 (
b10011100 1
b10011100 2
1#
#276
0#
#277
b10001010 3
b10001010 4
b1010 '
b1010 ,
1#
#278
0#
#279
b1011 '
b1011 ,
b10001011 3
b10001011 4
1#
#280
0#
#281
b10001100 3
b10001100 4
b1100 '
b1100 ,
1#
#282
0#
#283
b1101 '
b1101 ,
b10001101 3
b10001101 4
1#
#284
0#
#285
b10001110 3
b10001110 4
b1110 '
b1110 ,
1#
#286
0#
#287
b1111 '
b1111 ,
b10001111 3
b10001111 4
1#
#288
0#
#289
0*
b10010000 3
b10010000 4
b0 '
b0 ,
1#
#290
0#
#291
b1 '
b1 ,
b10010001 3
b10010001 4
1#
#292
0#
#293
b10010010 3
b10010010 4
b10 '
b10 ,
1#
#294
0#
#295
b11 '
b11 ,
b10010011 3
b10010011 4
1#
#296
0#
#297
b10010100 3
b10010100 4
b100 '
b100 ,
1#
#298
0#
#299
b101 '
b101 ,
b10010101 3
b10010101 4
1#
#300
0#
#301
b10010110 3
b10010110 4
b110 '
b110 ,
1#
#302
0#
#303
b111 '
b111 ,
b10010111 3
b10010111 4
1#
#304
0#
#305
b1010 )
b1010 +
b1010 .
b1010 /
1*
b10011000 3
b10011000 4
b1000 '
b1000 ,
1#
#306
0#
#307
b1001 '
b1001 ,
b10011001 3
b10011001 4
b10011111 (
b10011111 1
b10011111 2
1#
#308
0#
#309
b10011010 3
b10011010 4
b1010 '
b1010 ,
1#
#310
0#
#311
b1011 '
b1011 ,
b10011011 3
b10011011 4
1#
#312
0#
#313
b10011100 3
b10011100 4
b1100 '
b1100 ,
1#
#314
0#
#315
b1101 '
b1101 ,
b10011101 3
b10011101 4
1#
#316
0#
#317
b10011110 3
b10011110 4
b1110 '
b1110 ,
1#
#318
0#
#319
0"
b1111 '
b1111 ,
b10011111 3
b10011111 4
1#
#320
0#
#321
0*
b10100000 3
b10100000 4
b0 '
b0 ,
1#
#322
0#
#323
b1 '
b1 ,
b10100001 3
b10100001 4
1#
#324
0#
#325
b10100010 3
b10100010 4
b10 '
b10 ,
1#
#326
0#
#327
b11 '
b11 ,
b10100011 3
b10100011 4
1#
#328
0#
#329
b10100100 3
b10100100 4
b100 '
b100 ,
1#
#330
0#
#331
b101 '
b101 ,
b10100101 3
b10100101 4
1#
#332
0#
#333
b10100110 3
b10100110 4
b110 '
b110 ,
1#
#334
0#
#335
b111 '
b111 ,
b10100111 3
b10100111 4
1#
#336
0#
#337
b1011 )
b1011 +
b1011 .
b1011 /
1*
b10101000 3
b10101000 4
b1000 '
b1000 ,
1#
#338
0#
#339
b1001 '
b1001 ,
b10101001 3
b10101001 4
b10100010 (
b10100010 1
b10100010 2
1#
#340
0#
#341
b10101010 3
b10101010 4
b1010 '
b1010 ,
1#
#342
0#
#343
b1011 '
b1011 ,
b10101011 3
b10101011 4
1#
#344
0#
#345
b10101100 3
b10101100 4
b1100 '
b1100 ,
1#
#346
0#
#347
b1101 '
b1101 ,
b10101101 3
b10101101 4
1#
#348
0#
#349
b10101110 3
b10101110 4
b1110 '
b1110 ,
1#
#350
0#
#351
b1111 '
b1111 ,
b10101111 3
b10101111 4
1#
#352
0#
#353
0*
b10110000 3
b10110000 4
b0 '
b0 ,
1#
#354
0#
#355
b1 '
b1 ,
b10110001 3
b10110001 4
1#
#356
0#
#357
b10110010 3
b10110010 4
b10 '
b10 ,
1#
#358
0#
#359
b11 '
b11 ,
b10110011 3
b10110011 4
1#
#360
0#
#361
b10110100 3
b10110100 4
b100 '
b100 ,
1#
#362
0#
#363
b101 '
b101 ,
b10110101 3
b10110101 4
1#
#364
0#
#365
b10110110 3
b10110110 4
b110 '
b110 ,
1#
#366
0#
#367
b111 '
b111 ,
b10110111 3
b10110111 4
1#
#368
0#
#369
b1100 )
b1100 +
b1100 .
b1100 /
1*
b10111000 3
b10111000 4
b1000 '
b1000 ,
1#
#370
0#
#371
b1001 '
b1001 ,
b10111001 3
b10111001 4
b10100101 (
b10100101 1
b10100101 2
1#
#372
0#
#373
b10111010 3
b10111010 4
b1010 '
b1010 ,
1#
#374
0#
#375
b1011 '
b1011 ,
b10111011 3
b10111011 4
1#
#376
0#
#377
b10111100 3
b10111100 4
b1100 '
b1100 ,
1#
#378
0#
#379
b1101 '
b1101 ,
b10111101 3
b10111101 4
1#
#380
0#
#381
b10111110 3
b10111110 4
b1110 '
b1110 ,
1#
#382
0#
#383
b1111 '
b1111 ,
b10111111 3
b10111111 4
1#
#384
0#
#385
0*
b11000000 3
b11000000 4
b0 '
b0 ,
1#
#386
0#
#387
b1 '
b1 ,
b11000001 3
b11000001 4
1#
#388
0#
#389
b11000010 3
b11000010 4
b10 '
b10 ,
1#
#390
0#
#391
b11 '
b11 ,
b11000011 3
b11000011 4
1#
#392
0#
#393
b11000100 3
b11000100 4
b100 '
b100 ,
1#
#394
0#
#395
b101 '
b101 ,
b11000101 3
b11000101 4
1#
#396
0#
#397
b11000110 3
b11000110 4
b110 '
b110 ,
1#
#398
0#
#399
b111 '
b111 ,
b11000111 3
b11000111 4
1#
#400
0#
#401
b1101 )
b1101 +
b1101 .
b1101 /
1*
b11001000 3
b11001000 4
b1000 '
b1000 ,
1#
#402
0#
#403
b1001 '
b1001 ,
b11001001 3
b11001001 4
b10101000 (
b10101000 1
b10101000 2
1#
#404
0#
#405
b11001010 3
b11001010 4
b1010 '
b1010 ,
1#
#406
0#
#407
b1011 '
b1011 ,
b11001011 3
b11001011 4
1#
#408
0#
#409
b11001100 3
b11001100 4
b1100 '
b1100 ,
1#
#410
0#
#411
b1101 '
b1101 ,
b11001101 3
b11001101 4
1#
#412
0#
#413
b11001110 3
b11001110 4
b1110 '
b1110 ,
1#
#414
0#
#415
b1111 '
b1111 ,
b11001111 3
b11001111 4
1#
#416
0#
#417
0*
b11010000 3
b11010000 4
b0 '
b0 ,
1#
#418
0#
#419
b1 '
b1 ,
b11010001 3
b11010001 4
1#
#420
0#
#421
b11010010 3
b11010010 4
b10 '
b10 ,
1#
#422
0#
#423
b11 '
b11 ,
b11010011 3
b11010011 4
1#
#424
0#
#425
b11010100 3
b11010100 4
b100 '
b100 ,
1#
#426
0#
#427
b101 '
b101 ,
b11010101 3
b11010101 4
1#
#428
0#
#429
b11010110 3
b11010110 4
b110 '
b110 ,
1#
#430
0#
#431
b111 '
b111 ,
b11010111 3
b11010111 4
1#
#432
0#
#433
b1110 )
b1110 +
b1110 .
b1110 /
1*
b11011000 3
b11011000 4
b1000 '
b1000 ,
1#
#434
0#
#435
b1001 '
b1001 ,
b11011001 3
b11011001 4
b10101011 (
b10101011 1
b10101011 2
1#
#436
0#
#437
b11011010 3
b11011010 4
b1010 '
b1010 ,
1#
#438
0#
#439
b1011 '
b1011 ,
b11011011 3
b11011011 4
1#
#440
0#
#441
b11011100 3
b11011100 4
b1100 '
b1100 ,
1#
#442
0#
#443
b1101 '
b1101 ,
b11011101 3
b11011101 4
1#
#444
0#
#445
b11011110 3
b11011110 4
b1110 '
b1110 ,
1#
#446
0#
#447
b1111 '
b1111 ,
b11011111 3
b11011111 4
1#
#448
0#
#449
0*
b11100000 3
b11100000 4
b0 '
b0 ,
1#
#450
0#
#451
b1 '
b1 ,
b11100001 3
b11100001 4
1#
#452
0#
#453
b11100010 3
b11100010 4
b10 '
b10 ,
1#
#454
0#
#455
b11 '
b11 ,
b11100011 3
b11100011 4
1#
#456
0#
#457
b11100100 3
b11100100 4
b100 '
b100 ,
1#
#458
0#
#459
b101 '
b101 ,
b11100101 3
b11100101 4
1#
#460
0#
#461
b11100110 3
b11100110 4
b110 '
b110 ,
1#
#462
0#
#463
b111 '
b111 ,
b11100111 3
b11100111 4
1#
#464
0#
#465
b1111 )
b1111 +
b1111 .
b1111 /
1*
b11101000 3
b11101000 4
b1000 '
b1000 ,
1#
#466
0#
#467
b1001 '
b1001 ,
b11101001 3
b11101001 4
b10101110 (
b10101110 1
b10101110 2
1#
#468
0#
#469
b11101010 3
b11101010 4
b1010 '
b1010 ,
1#
#470
0#
#471
b1011 '
b1011 ,
b11101011 3
b11101011 4
1#
#472
0#
#473
b11101100 3
b11101100 4
b1100 '
b1100 ,
1#
#474
0#
#475
b1101 '
b1101 ,
b11101101 3
b11101101 4
1#
#476
0#
#477
b11101110 3
b11101110 4
b1110 '
b1110 ,
1#
#478
0#
#479
b1111 '
b1111 ,
b11101111 3
b11101111 4
1#
#480
0#
#481
0*
b11110000 3
b11110000 4
b0 '
b0 ,
1#
#482
0#
#483
b1 '
b1 ,
b11110001 3
b11110001 4
1#
#484
0#
#485
b11110010 3
b11110010 4
b10 '
b10 ,
1#
#486
0#
#487
b11 '
b11 ,
b11110011 3
b11110011 4
1#
#488
0#
#489
b11110100 3
b11110100 4
b100 '
b100 ,
1#
#490
0#
#491
b101 '
b101 ,
b11110101 3
b11110101 4
1#
#492
0#
#493
b11110110 3
b11110110 4
b110 '
b110 ,
1#
#494
0#
#495
b111 '
b111 ,
b11110111 3
b11110111 4
1#
#496
0#
#497
b10000 )
b10000 +
b10000 .
b10000 /
1*
b11111000 3
b11111000 4
b1000 '
b1000 ,
1#
#498
0#
#499
b1001 '
b1001 ,
b11111001 3
b11111001 4
b10110000 (
b10110000 1
b10110000 2
1#
#500
0#
#501
b11111010 3
b11111010 4
b1010 '
b1010 ,
1#
#502
0#
#503
b1011 '
b1011 ,
b11111011 3
b11111011 4
1#
#504
0#
#505
b11111100 3
b11111100 4
b1100 '
b1100 ,
1#
#506
0#
#507
b1101 '
b1101 ,
b11111101 3
b11111101 4
1#
#508
0#
#509
b11111110 3
b11111110 4
b1110 '
b1110 ,
1#
#510
0#
#511
b1111 '
b1111 ,
b11111111 3
b11111111 4
1#
#512
0#
#513
1"
0*
b0 3
b0 4
b0 '
b0 ,
1#
#514
0#
#515
b1 '
b1 ,
b1 3
b1 4
1#
#516
0#
#517
b10 3
b10 4
b10 '
b10 ,
1#
#518
0#
#519
b11 '
b11 ,
b11 3
b11 4
1#
#520
0#
#521
b100 3
b100 4
b100 '
b100 ,
1#
#522
0#
#523
b101 '
b101 ,
b101 3
b101 4
1#
#524
0#
#525
b110 3
b110 4
b110 '
b110 ,
1#
#526
0#
#527
b111 '
b111 ,
b111 3
b111 4
1#
#528
0#
#529
b10001 )
b10001 +
b10001 .
b10001 /
1*
b1000 3
b1000 4
b1000 '
b1000 ,
1#
#530
0#
#531
b1001 '
b1001 ,
b1001 3
b1001 4
b10110011 (
b10110011 1
b10110011 2
1#
#532
0#
#533
b1010 3
b1010 4
b1010 '
b1010 ,
1#
#534
0#
#535
b1011 '
b1011 ,
b1011 3
b1011 4
1#
#536
0#
#537
b1100 3
b1100 4
b1100 '
b1100 ,
1#
#538
0#
#539
b1101 '
b1101 ,
b1101 3
b1101 4
1#
#540
0#
#541
b1110 3
b1110 4
b1110 '
b1110 ,
1#
#542
0#
#543
b1111 '
b1111 ,
b1111 3
b1111 4
1#
#544
0#
#545
0*
b10000 3
b10000 4
b0 '
b0 ,
1#
#546
0#
#547
b1 '
b1 ,
b10001 3
b10001 4
1#
#548
0#
#549
b10010 3
b10010 4
b10 '
b10 ,
1#
#550
0#
#551
b11 '
b11 ,
b10011 3
b10011 4
1#
#552
0#
#553
b10100 3
b10100 4
b100 '
b100 ,
1#
#554
0#
#555
b101 '
b101 ,
b10101 3
b10101 4
1#
#556
0#
#557
b10110 3
b10110 4
b110 '
b110 ,
1#
#558
0#
#559
b111 '
b111 ,
b10111 3
b10111 4
1#
#560
0#
#561
b10010 )
b10010 +
b10010 .
b10010 /
1*
b11000 3
b11000 4
b1000 '
b1000 ,
1#
#562
0#
#563
b1001 '
b1001 ,
b11001 3
b11001 4
b10110110 (
b10110110 1
b10110110 2
1#
#564
0#
#565
b11010 3
b11010 4
b1010 '
b1010 ,
1#
#566
0#
#567
b1011 '
b1011 ,
b11011 3
b11011 4
1#
#568
0#
#569
b11100 3
b11100 4
b1100 '
b1100 ,
1#
#570
0#
#571
b1101 '
b1101 ,
b11101 3
b11101 4
1#
#572
0#
#573
b11110 3
b11110 4
b1110 '
b1110 ,
1#
#574
0#
#575
b1111 '
b1111 ,
b11111 3
b11111 4
1#
#576
0#
